plotagain/__init__.py
plotagain/iddict.py
plotagain/pyplotcall.py
plotagain/saveplotcontext.py
plotagain/script_template.txt
plotagain/utils.py
plotagain/data-save-dir/make_plot.py
plotagain-1.0.6.dist-info/METADATA
plotagain-1.0.6.dist-info/WHEEL
plotagain-1.0.6.dist-info/top_level.txt
plotagain-1.0.6.dist-info/RECORD
