Metadata-Version: 2.1
Name: plotagain
Version: 1.0.6
Summary: A helper tool for matplotlib. Provides a contextmanager which automatically saves data used to make plots and automatically generates a script to re-load and re-plot this data at a later stage.
Author-email: Jeremy John Henry Wilkinson <jero.wilkinson@gmail.com>
License: BSD-3-Clause
Project-URL: Homepage, https://bitbucket.org/jjhw3/plotagain/
Keywords: save data,matplotlib,plt
Classifier: Framework :: Matplotlib
Classifier: Programming Language :: Python :: 3
Requires-Python: >=3.0
Requires-Dist: matplotlib
Requires-Dist: numpy
